app/__init__.py
app/main.py
asi_weather-2.2.8.dist-info/METADATA
asi_weather-2.2.8.dist-info/WHEEL
asi_weather-2.2.8.dist-info/top_level.txt
asi_weather-2.2.8.dist-info/RECORD
